{"pagelen": 100, "values": [{"changes": {"state": {"new": "duplicate", "old": "new"}}, "links": {"self": {"href": "data/repositories/osrf/drcsim/issues/354/changes/6898703.json"}, "html": {"href": "#!/osrf/drcsim/issues/354#comment-6898703"}}, "issue": {"links": {"self": {"href": "data/repositories/osrf/drcsim/issues/354.json"}}, "type": "issue", "id": 354, "repository": {"links": {"self": {"href": "data/repositories/osrf/drcsim.json"}, "html": {"href": "#!/osrf/drcsim"}, "avatar": {"href": "data/bytebucket.org/ravatar/{247b5408-ae91-4e3c-b2f9-a21994658d11}ts=c_plus_plus"}}, "type": "repository", "name": "drcsim", "full_name": "osrf/drcsim", "uuid": "{247b5408-ae91-4e3c-b2f9-a21994658d11}"}, "title": "atlas_v3_v1_sandia model blows up where old one doesn't"}, "created_on": "2013-11-14T17:29:50.400789+00:00", "user": {"display_name": "Brian Gerkey", "uuid": "{3d8b5763-9dad-4be7-85c2-a7ab6cd49173}", "links": {"self": {"href": "https://api.bitbucket.org/2.0/users/%7B3d8b5763-9dad-4be7-85c2-a7ab6cd49173%7D"}, "html": {"href": "https://bitbucket.org/%7B3d8b5763-9dad-4be7-85c2-a7ab6cd49173%7D/"}, "avatar": {"href": "https://avatar-management--avatars.us-west-2.prod.public.atl-paas.net/557058:2e35028e-9ad8-4d6a-a3a5-275159a304a9/5fa9ec73-0fec-4860-a202-e34ae23b6a12/128"}}, "nickname": "Brian Gerkey", "type": "user", "account_id": "557058:2e35028e-9ad8-4d6a-a3a5-275159a304a9"}, "message": {"raw": "Duplicate of #355.", "markup": "markdown", "html": "<p>Duplicate of <a href=\"#!/osrf/drcsim/issues/355/atlas_v3-blows-up-when-kp_velocity-0\" rel=\"nofollow\" title=\"atlas_v3 blows up when kp_velocity &gt; 0 commanded for ankles\" class=\"ap-connect-link\"><s>#355</s></a>.</p>", "type": "rendered"}, "type": "issue_change", "id": 6898703}], "page": 1, "size": 1}