{"pagelen": 100, "values": [{"links": {"self": {"href": "data/repositories/osrf/drcsim/issues/470/comments/14693913.json"}, "html": {"href": "#!/osrf/drcsim/issues/470#comment-14693913"}}, "issue": {"links": {"self": {"href": "data/repositories/osrf/drcsim/issues/470.json"}}, "type": "issue", "id": 470, "repository": {"links": {"self": {"href": "data/repositories/osrf/drcsim.json"}, "html": {"href": "#!/osrf/drcsim"}, "avatar": {"href": "data/bytebucket.org/ravatar/{247b5408-ae91-4e3c-b2f9-a21994658d11}ts=c_plus_plus"}}, "type": "repository", "name": "drcsim", "full_name": "osrf/drcsim", "uuid": "{247b5408-ae91-4e3c-b2f9-a21994658d11}"}, "title": "model issues - corrupted view with debian 4.2.4-1~trusty and 3.0.2 library"}, "content": {"raw": "Screenshot failed to attach properly the first time", "markup": "markdown", "html": "<p>Screenshot failed to attach properly the first time</p>", "type": "rendered"}, "created_on": "2015-01-08T21:03:46.516685+00:00", "user": {"display_name": "David Conner", "uuid": "{4375dc4a-9371-4c51-973e-1f1d045590c5}", "links": {"self": {"href": "https://api.bitbucket.org/2.0/users/%7B4375dc4a-9371-4c51-973e-1f1d045590c5%7D"}, "html": {"href": "https://bitbucket.org/%7B4375dc4a-9371-4c51-973e-1f1d045590c5%7D/"}, "avatar": {"href": "https://bitbucket.org/account/dcconner/avatar/"}}, "nickname": "dcconner", "type": "user", "account_id": null}, "updated_on": null, "type": "issue_comment", "id": 14693913}, {"links": {"self": {"href": "data/repositories/osrf/drcsim/issues/470/comments/14694338.json"}, "html": {"href": "#!/osrf/drcsim/issues/470#comment-14694338"}}, "issue": {"links": {"self": {"href": "data/repositories/osrf/drcsim/issues/470.json"}}, "type": "issue", "id": 470, "repository": {"links": {"self": {"href": "data/repositories/osrf/drcsim.json"}, "html": {"href": "#!/osrf/drcsim"}, "avatar": {"href": "data/bytebucket.org/ravatar/{247b5408-ae91-4e3c-b2f9-a21994658d11}ts=c_plus_plus"}}, "type": "repository", "name": "drcsim", "full_name": "osrf/drcsim", "uuid": "{247b5408-ae91-4e3c-b2f9-a21994658d11}"}, "title": "model issues - corrupted view with debian 4.2.4-1~trusty and 3.0.2 library"}, "content": {"raw": "Which launch file is this?", "markup": "markdown", "html": "<p>Which launch file is this?</p>", "type": "rendered"}, "created_on": "2015-01-08T21:28:14.600000+00:00", "user": {"display_name": "Steve Peters", "uuid": "{2ccfed09-18b8-4921-8d58-15ef01092802}", "links": {"self": {"href": "https://api.bitbucket.org/2.0/users/%7B2ccfed09-18b8-4921-8d58-15ef01092802%7D"}, "html": {"href": "https://bitbucket.org/%7B2ccfed09-18b8-4921-8d58-15ef01092802%7D/"}, "avatar": {"href": "data/secure.gravatar.com/avatar/1fb4816dad9e68337d3096f750951f6cd=httpsavatar-management--avatars.us-west-2.prod.public.atl-paas.netinitialsSP-1.png"}}, "nickname": "Steven Peters", "type": "user", "account_id": "557058:5de38267-b118-494c-aa76-4fab35448816"}, "updated_on": null, "type": "issue_comment", "id": 14694338}, {"links": {"self": {"href": "data/repositories/osrf/drcsim/issues/470/comments/14695159.json"}, "html": {"href": "#!/osrf/drcsim/issues/470#comment-14695159"}}, "issue": {"links": {"self": {"href": "data/repositories/osrf/drcsim/issues/470.json"}}, "type": "issue", "id": 470, "repository": {"links": {"self": {"href": "data/repositories/osrf/drcsim.json"}, "html": {"href": "#!/osrf/drcsim"}, "avatar": {"href": "data/bytebucket.org/ravatar/{247b5408-ae91-4e3c-b2f9-a21994658d11}ts=c_plus_plus"}}, "type": "repository", "name": "drcsim", "full_name": "osrf/drcsim", "uuid": "{247b5408-ae91-4e3c-b2f9-a21994658d11}"}, "title": "model issues - corrupted view with debian 4.2.4-1~trusty and 3.0.2 library"}, "content": {"raw": "Running default instructions from the web for library 3.0.2.\n\nI updated another machine and did not see this problem.  Therefore it is likely a graphics driver issue.  Old drcsim ran fine on the machine that had this issue, but I'll try re-installing the NVIDIA drivers and try again.\n", "markup": "markdown", "html": "<p>Running default instructions from the web for library 3.0.2.</p>\n<p>I updated another machine and did not see this problem.  Therefore it is likely a graphics driver issue.  Old drcsim ran fine on the machine that had this issue, but I'll try re-installing the NVIDIA drivers and try again.</p>", "type": "rendered"}, "created_on": "2015-01-08T22:14:15.837670+00:00", "user": {"display_name": "David Conner", "uuid": "{4375dc4a-9371-4c51-973e-1f1d045590c5}", "links": {"self": {"href": "https://api.bitbucket.org/2.0/users/%7B4375dc4a-9371-4c51-973e-1f1d045590c5%7D"}, "html": {"href": "https://bitbucket.org/%7B4375dc4a-9371-4c51-973e-1f1d045590c5%7D/"}, "avatar": {"href": "https://bitbucket.org/account/dcconner/avatar/"}}, "nickname": "dcconner", "type": "user", "account_id": null}, "updated_on": null, "type": "issue_comment", "id": 14695159}, {"links": {"self": {"href": "data/repositories/osrf/drcsim/issues/470/comments/14718395.json"}, "html": {"href": "#!/osrf/drcsim/issues/470#comment-14718395"}}, "issue": {"links": {"self": {"href": "data/repositories/osrf/drcsim/issues/470.json"}}, "type": "issue", "id": 470, "repository": {"links": {"self": {"href": "data/repositories/osrf/drcsim.json"}, "html": {"href": "#!/osrf/drcsim"}, "avatar": {"href": "data/bytebucket.org/ravatar/{247b5408-ae91-4e3c-b2f9-a21994658d11}ts=c_plus_plus"}}, "type": "repository", "name": "drcsim", "full_name": "osrf/drcsim", "uuid": "{247b5408-ae91-4e3c-b2f9-a21994658d11}"}, "title": "model issues - corrupted view with debian 4.2.4-1~trusty and 3.0.2 library"}, "content": {"raw": "Confirmed NVIDIA driver issue", "markup": "markdown", "html": "<p>Confirmed NVIDIA driver issue</p>", "type": "rendered"}, "created_on": "2015-01-09T21:29:05.814195+00:00", "user": {"display_name": "David Conner", "uuid": "{4375dc4a-9371-4c51-973e-1f1d045590c5}", "links": {"self": {"href": "https://api.bitbucket.org/2.0/users/%7B4375dc4a-9371-4c51-973e-1f1d045590c5%7D"}, "html": {"href": "https://bitbucket.org/%7B4375dc4a-9371-4c51-973e-1f1d045590c5%7D/"}, "avatar": {"href": "https://bitbucket.org/account/dcconner/avatar/"}}, "nickname": "dcconner", "type": "user", "account_id": null}, "updated_on": null, "type": "issue_comment", "id": 14718395}, {"links": {"self": {"href": "data/repositories/osrf/drcsim/issues/470/comments/14718404.json"}, "html": {"href": "#!/osrf/drcsim/issues/470#comment-14718404"}}, "issue": {"links": {"self": {"href": "data/repositories/osrf/drcsim/issues/470.json"}}, "type": "issue", "id": 470, "repository": {"links": {"self": {"href": "data/repositories/osrf/drcsim.json"}, "html": {"href": "#!/osrf/drcsim"}, "avatar": {"href": "data/bytebucket.org/ravatar/{247b5408-ae91-4e3c-b2f9-a21994658d11}ts=c_plus_plus"}}, "type": "repository", "name": "drcsim", "full_name": "osrf/drcsim", "uuid": "{247b5408-ae91-4e3c-b2f9-a21994658d11}"}, "title": "model issues - corrupted view with debian 4.2.4-1~trusty and 3.0.2 library"}, "content": {"raw": "Verified that this was driver issue", "markup": "markdown", "html": "<p>Verified that this was driver issue</p>", "type": "rendered"}, "created_on": "2015-01-09T21:29:27.250648+00:00", "user": {"display_name": "David Conner", "uuid": "{4375dc4a-9371-4c51-973e-1f1d045590c5}", "links": {"self": {"href": "https://api.bitbucket.org/2.0/users/%7B4375dc4a-9371-4c51-973e-1f1d045590c5%7D"}, "html": {"href": "https://bitbucket.org/%7B4375dc4a-9371-4c51-973e-1f1d045590c5%7D/"}, "avatar": {"href": "https://bitbucket.org/account/dcconner/avatar/"}}, "nickname": "dcconner", "type": "user", "account_id": null}, "updated_on": null, "type": "issue_comment", "id": 14718404}], "page": 1, "size": 5}