{"links": {"self": {"href": "data/repositories/osrf/drcsim/issues/398/comments/7411060.json"}, "html": {"href": "#!/osrf/drcsim/issues/398#comment-7411060"}}, "issue": {"links": {"self": {"href": "data/repositories/osrf/drcsim/issues/398.json"}}, "type": "issue", "id": 398, "repository": {"links": {"self": {"href": "data/repositories/osrf/drcsim.json"}, "html": {"href": "#!/osrf/drcsim"}, "avatar": {"href": "data/bytebucket.org/ravatar/{247b5408-ae91-4e3c-b2f9-a21994658d11}ts=c_plus_plus"}}, "type": "repository", "name": "drcsim", "full_name": "osrf/drcsim", "uuid": "{247b5408-ae91-4e3c-b2f9-a21994658d11}"}, "title": "update_irobot_hand Left Hand Rotate 180deg"}, "content": {"raw": "Does below match hardware?\n\n![updated irobot hand configuration](https://dl.dropbox.com/s/0wq07uwgbrcz8vd/drcsim_issue_398.png)", "markup": "markdown", "html": "<p>Does below match hardware?</p>\n<p><img alt=\"updated irobot hand configuration\" src=\"https://dl.dropbox.com/s/0wq07uwgbrcz8vd/drcsim_issue_398.png\" /></p>", "type": "rendered"}, "created_on": "2013-12-18T21:55:05.239665+00:00", "user": {"display_name": "John Hsu", "uuid": "{0a186eae-abf0-4514-a951-23db5eccc286}", "links": {"self": {"href": "https://api.bitbucket.org/2.0/users/%7B0a186eae-abf0-4514-a951-23db5eccc286%7D"}, "html": {"href": "https://bitbucket.org/%7B0a186eae-abf0-4514-a951-23db5eccc286%7D/"}, "avatar": {"href": "https://avatar-management--avatars.us-west-2.prod.public.atl-paas.net/557058:f3968cd3-4910-4384-8349-482a6c7889ec/5445ce6e-6273-47f0-84eb-621c86ca11cb/128"}}, "nickname": "hsu", "type": "user", "account_id": "557058:f3968cd3-4910-4384-8349-482a6c7889ec"}, "updated_on": null, "type": "issue_comment", "id": 7411060}