{"links": {"self": {"href": "data/repositories/osrf/drcsim/issues/486/comments/15677983.json"}, "html": {"href": "#!/osrf/drcsim/issues/486#comment-15677983"}}, "issue": {"links": {"self": {"href": "data/repositories/osrf/drcsim/issues/486.json"}}, "type": "issue", "id": 486, "repository": {"links": {"self": {"href": "data/repositories/osrf/drcsim.json"}, "html": {"href": "#!/osrf/drcsim"}, "avatar": {"href": "data/bytebucket.org/ravatar/{247b5408-ae91-4e3c-b2f9-a21994658d11}ts=c_plus_plus"}}, "type": "repository", "name": "drcsim", "full_name": "osrf/drcsim", "uuid": "{247b5408-ae91-4e3c-b2f9-a21994658d11}"}, "title": "DART not working on DRCSim"}, "content": {"raw": "I can confirm that the arguiment\n\n         extra_gazebo_args:=\"-e dart\"\n\n is being ignored.\nJust in case, I also commented the part in my .world file where physics was configured.\n\nIf I change some ODE related parameters I affect the simulation. This would not happen if DART was used under the hood.", "markup": "markdown", "html": "<p>I can confirm that the arguiment</p>\n<div class=\"codehilite\"><pre><span></span>     extra_gazebo_args:=&quot;-e dart&quot;\n</pre></div>\n\n\n<p>is being ignored.\nJust in case, I also commented the part in my .world file where physics was configured.</p>\n<p>If I change some ODE related parameters I affect the simulation. This would not happen if DART was used under the hood.</p>", "type": "rendered"}, "created_on": "2015-02-13T17:31:29.294006+00:00", "user": {"display_name": "Davide Faconti", "uuid": "{3bbc1820-fdbe-4162-b25e-fab777cc0f8d}", "links": {"self": {"href": "https://api.bitbucket.org/2.0/users/%7B3bbc1820-fdbe-4162-b25e-fab777cc0f8d%7D"}, "html": {"href": "https://bitbucket.org/%7B3bbc1820-fdbe-4162-b25e-fab777cc0f8d%7D/"}, "avatar": {"href": "https://avatar-management--avatars.us-west-2.prod.public.atl-paas.net/557058:1062128f-7772-4ea3-89d5-5ef7858df793/e350d3ea-077e-4a95-b81c-d41dc0012942/128"}}, "nickname": "facontidavide", "type": "user", "account_id": "557058:1062128f-7772-4ea3-89d5-5ef7858df793"}, "updated_on": null, "type": "issue_comment", "id": 15677983}