{"links": {"self": {"href": "data/repositories/osrf/drcsim/pullrequests/173/comments/182186.json"}, "html": {"href": "#!/osrf/drcsim/pull-requests/173/_/diff#comment-182186"}}, "parent": {"id": 182184, "links": {"self": {"href": "data/repositories/osrf/drcsim/pullrequests/173/comments/182184.json"}, "html": {"href": "#!/osrf/drcsim/pull-requests/173/_/diff#comment-182184"}}}, "deleted": false, "pullrequest": {"type": "pullrequest", "id": 173, "links": {"self": {"href": "data/repositories/osrf/drcsim/pullrequests/173.json"}, "html": {"href": "#!/osrf/drcsim/pull-requests/173"}}, "title": "AtlasSimInterface_1.0.5 (contains udp_tweak pull request #169)"}, "content": {"raw": "``ros/atlas_utils/scripts/run_gzserver_gdb``\n\nas well ;)\nrun_gzserver seems to be doing what run_gzserver_gdb should be doing (i.e. launch gzserver with gdb)", "markup": "markdown", "html": "<p><code>ros/atlas_utils/scripts/run_gzserver_gdb</code></p>\n<p>as well ;)\nrun_gzserver seems to be doing what run_gzserver_gdb should be doing (i.e. launch gzserver with gdb)</p>", "type": "rendered"}, "created_on": "2013-04-03T16:58:40.834747+00:00", "user": {"display_name": "Thomas Koletschka", "uuid": "{b33092ac-6376-48d1-9803-d9e6de445d1a}", "links": {"self": {"href": "https://api.bitbucket.org/2.0/users/%7Bb33092ac-6376-48d1-9803-d9e6de445d1a%7D"}, "html": {"href": "https://bitbucket.org/%7Bb33092ac-6376-48d1-9803-d9e6de445d1a%7D/"}, "avatar": {"href": "https://bitbucket.org/account/thomasko/avatar/"}}, "nickname": "thomasko", "type": "user", "account_id": null}, "updated_on": "2013-04-03T17:04:44.936998+00:00", "type": "pullrequest_comment", "id": 182186}