{"pagelen": 100, "values": [{"links": {"self": {"href": "data/repositories/osrf/drcsim/issues/255/comments/3988619.json"}, "html": {"href": "#!/osrf/drcsim/issues/255#comment-3988619"}}, "issue": {"links": {"self": {"href": "data/repositories/osrf/drcsim/issues/255.json"}}, "type": "issue", "id": 255, "repository": {"links": {"self": {"href": "data/repositories/osrf/drcsim.json"}, "html": {"href": "#!/osrf/drcsim"}, "avatar": {"href": "data/bytebucket.org/ravatar/{247b5408-ae91-4e3c-b2f9-a21994658d11}ts=c_plus_plus"}}, "type": "repository", "name": "drcsim", "full_name": "osrf/drcsim", "uuid": "{247b5408-ae91-4e3c-b2f9-a21994658d11}"}, "title": "Atlas URDF and SDF collision geometries vastly different"}, "content": {"raw": "..forgot to add gazebo collision geom image", "markup": "markdown", "html": "<p>..forgot to add gazebo collision geom image</p>", "type": "rendered"}, "created_on": "2013-05-07T14:11:36.898196+00:00", "user": {"display_name": "Stefan Kohlbrecher", "uuid": "{db06b03e-7b31-4483-9018-534df5bd723f}", "links": {"self": {"href": "https://api.bitbucket.org/2.0/users/%7Bdb06b03e-7b31-4483-9018-534df5bd723f%7D"}, "html": {"href": "https://bitbucket.org/%7Bdb06b03e-7b31-4483-9018-534df5bd723f%7D/"}, "avatar": {"href": "data/secure.gravatar.com/avatar/414f1c364e6406dde31a6ef70fbd3d21d=httpsavatar-management--avatars.us-west-2.prod.public.atl-paas.netinitialsSK-6.png"}}, "nickname": "Stefan_Kohlbrecher", "type": "user", "account_id": "557058:e39b6a62-9eb0-45ca-b27e-4f6445009d3f"}, "updated_on": null, "type": "issue_comment", "id": 3988619}, {"links": {"self": {"href": "data/repositories/osrf/drcsim/issues/255/comments/3989178.json"}, "html": {"href": "#!/osrf/drcsim/issues/255#comment-3989178"}}, "issue": {"links": {"self": {"href": "data/repositories/osrf/drcsim/issues/255.json"}}, "type": "issue", "id": 255, "repository": {"links": {"self": {"href": "data/repositories/osrf/drcsim.json"}, "html": {"href": "#!/osrf/drcsim"}, "avatar": {"href": "data/bytebucket.org/ravatar/{247b5408-ae91-4e3c-b2f9-a21994658d11}ts=c_plus_plus"}}, "type": "repository", "name": "drcsim", "full_name": "osrf/drcsim", "uuid": "{247b5408-ae91-4e3c-b2f9-a21994658d11}"}, "title": "Atlas URDF and SDF collision geometries vastly different"}, "content": {"raw": "Stefan, this is due to urdf / rviz (idk which one it is, I think urdf?) only supporting one collision model per link. So this is more of a problem on ROS' side to fix I think (but now that ROS is part of OSRF it's at least the correct organization's issue tracker ;P ).", "markup": "markdown", "html": "<p>Stefan, this is due to urdf / rviz (idk which one it is, I think urdf?) only supporting one collision model per link. So this is more of a problem on ROS' side to fix I think (but now that ROS is part of OSRF it's at least the correct organization's issue tracker ;P ).</p>", "type": "rendered"}, "created_on": "2013-05-07T14:49:27.976854+00:00", "user": {"display_name": "Thomas Koletschka", "uuid": "{b33092ac-6376-48d1-9803-d9e6de445d1a}", "links": {"self": {"href": "https://api.bitbucket.org/2.0/users/%7Bb33092ac-6376-48d1-9803-d9e6de445d1a%7D"}, "html": {"href": "https://bitbucket.org/%7Bb33092ac-6376-48d1-9803-d9e6de445d1a%7D/"}, "avatar": {"href": "https://bitbucket.org/account/thomasko/avatar/"}}, "nickname": "thomasko", "type": "user", "account_id": null}, "updated_on": null, "type": "issue_comment", "id": 3989178}, {"links": {"self": {"href": "data/repositories/osrf/drcsim/issues/255/comments/3989334.json"}, "html": {"href": "#!/osrf/drcsim/issues/255#comment-3989334"}}, "issue": {"links": {"self": {"href": "data/repositories/osrf/drcsim/issues/255.json"}}, "type": "issue", "id": 255, "repository": {"links": {"self": {"href": "data/repositories/osrf/drcsim.json"}, "html": {"href": "#!/osrf/drcsim"}, "avatar": {"href": "data/bytebucket.org/ravatar/{247b5408-ae91-4e3c-b2f9-a21994658d11}ts=c_plus_plus"}}, "type": "repository", "name": "drcsim", "full_name": "osrf/drcsim", "uuid": "{247b5408-ae91-4e3c-b2f9-a21994658d11}"}, "title": "Atlas URDF and SDF collision geometries vastly different"}, "content": {"raw": "I'm aware of this disctinction, but seeing how both URDF and SDF are part of what gets distributed to teams with drcsim, I'd expect both models to be reasonably similar. If that expectation is wrong, I just have to know it, so we can fix it ourselves.", "markup": "markdown", "html": "<p>I'm aware of this disctinction, but seeing how both URDF and SDF are part of what gets distributed to teams with drcsim, I'd expect both models to be reasonably similar. If that expectation is wrong, I just have to know it, so we can fix it ourselves.</p>", "type": "rendered"}, "created_on": "2013-05-07T15:04:45.794293+00:00", "user": {"display_name": "Stefan Kohlbrecher", "uuid": "{db06b03e-7b31-4483-9018-534df5bd723f}", "links": {"self": {"href": "https://api.bitbucket.org/2.0/users/%7Bdb06b03e-7b31-4483-9018-534df5bd723f%7D"}, "html": {"href": "https://bitbucket.org/%7Bdb06b03e-7b31-4483-9018-534df5bd723f%7D/"}, "avatar": {"href": "data/secure.gravatar.com/avatar/414f1c364e6406dde31a6ef70fbd3d21d=httpsavatar-management--avatars.us-west-2.prod.public.atl-paas.netinitialsSK-6.png"}}, "nickname": "Stefan_Kohlbrecher", "type": "user", "account_id": "557058:e39b6a62-9eb0-45ca-b27e-4f6445009d3f"}, "updated_on": null, "type": "issue_comment", "id": 3989334}, {"links": {"self": {"href": "data/repositories/osrf/drcsim/issues/255/comments/3989530.json"}, "html": {"href": "#!/osrf/drcsim/issues/255#comment-3989530"}}, "issue": {"links": {"self": {"href": "data/repositories/osrf/drcsim/issues/255.json"}}, "type": "issue", "id": 255, "repository": {"links": {"self": {"href": "data/repositories/osrf/drcsim.json"}, "html": {"href": "#!/osrf/drcsim"}, "avatar": {"href": "data/bytebucket.org/ravatar/{247b5408-ae91-4e3c-b2f9-a21994658d11}ts=c_plus_plus"}}, "type": "repository", "name": "drcsim", "full_name": "osrf/drcsim", "uuid": "{247b5408-ae91-4e3c-b2f9-a21994658d11}"}, "title": "Atlas URDF and SDF collision geometries vastly different"}, "content": {"raw": "Thanks for reporting the issue,  I've ticketed this issue in [rviz issue tracker](https://github.com/ros-visualization/rviz/issues/633).\n", "markup": "markdown", "html": "<p>Thanks for reporting the issue,  I've ticketed this issue in <a data-is-external-link=\"true\" href=\"https://github.com/ros-visualization/rviz/issues/633\" rel=\"nofollow\">rviz issue tracker</a>.</p>", "type": "rendered"}, "created_on": "2013-05-07T15:19:05.258499+00:00", "user": {"display_name": "John Hsu", "uuid": "{0a186eae-abf0-4514-a951-23db5eccc286}", "links": {"self": {"href": "https://api.bitbucket.org/2.0/users/%7B0a186eae-abf0-4514-a951-23db5eccc286%7D"}, "html": {"href": "https://bitbucket.org/%7B0a186eae-abf0-4514-a951-23db5eccc286%7D/"}, "avatar": {"href": "https://avatar-management--avatars.us-west-2.prod.public.atl-paas.net/557058:f3968cd3-4910-4384-8349-482a6c7889ec/5445ce6e-6273-47f0-84eb-621c86ca11cb/128"}}, "nickname": "hsu", "type": "user", "account_id": "557058:f3968cd3-4910-4384-8349-482a6c7889ec"}, "updated_on": null, "type": "issue_comment", "id": 3989530}, {"links": {"self": {"href": "data/repositories/osrf/drcsim/issues/255/comments/3989576.json"}, "html": {"href": "#!/osrf/drcsim/issues/255#comment-3989576"}}, "issue": {"links": {"self": {"href": "data/repositories/osrf/drcsim/issues/255.json"}}, "type": "issue", "id": 255, "repository": {"links": {"self": {"href": "data/repositories/osrf/drcsim.json"}, "html": {"href": "#!/osrf/drcsim"}, "avatar": {"href": "data/bytebucket.org/ravatar/{247b5408-ae91-4e3c-b2f9-a21994658d11}ts=c_plus_plus"}}, "type": "repository", "name": "drcsim", "full_name": "osrf/drcsim", "uuid": "{247b5408-ae91-4e3c-b2f9-a21994658d11}"}, "title": "Atlas URDF and SDF collision geometries vastly different"}, "content": {"raw": "the collision geometries should be the same in SDF and URDF.  The differences between gazebo and rviz visualization is due to rviz not displaying all collision geometries specified in URDF.  Please reopen this issue if the collision/visual geometries are physically different between SDF and URDF.  Thanks.", "markup": "markdown", "html": "<p>the collision geometries should be the same in SDF and URDF.  The differences between gazebo and rviz visualization is due to rviz not displaying all collision geometries specified in URDF.  Please reopen this issue if the collision/visual geometries are physically different between SDF and URDF.  Thanks.</p>", "type": "rendered"}, "created_on": "2013-05-07T15:22:30.974874+00:00", "user": {"display_name": "John Hsu", "uuid": "{0a186eae-abf0-4514-a951-23db5eccc286}", "links": {"self": {"href": "https://api.bitbucket.org/2.0/users/%7B0a186eae-abf0-4514-a951-23db5eccc286%7D"}, "html": {"href": "https://bitbucket.org/%7B0a186eae-abf0-4514-a951-23db5eccc286%7D/"}, "avatar": {"href": "https://avatar-management--avatars.us-west-2.prod.public.atl-paas.net/557058:f3968cd3-4910-4384-8349-482a6c7889ec/5445ce6e-6273-47f0-84eb-621c86ca11cb/128"}}, "nickname": "hsu", "type": "user", "account_id": "557058:f3968cd3-4910-4384-8349-482a6c7889ec"}, "updated_on": null, "type": "issue_comment", "id": 3989576}, {"links": {"self": {"href": "data/repositories/osrf/drcsim/issues/255/comments/3990848.json"}, "html": {"href": "#!/osrf/drcsim/issues/255#comment-3990848"}}, "issue": {"links": {"self": {"href": "data/repositories/osrf/drcsim/issues/255.json"}}, "type": "issue", "id": 255, "repository": {"links": {"self": {"href": "data/repositories/osrf/drcsim.json"}, "html": {"href": "#!/osrf/drcsim"}, "avatar": {"href": "data/bytebucket.org/ravatar/{247b5408-ae91-4e3c-b2f9-a21994658d11}ts=c_plus_plus"}}, "type": "repository", "name": "drcsim", "full_name": "osrf/drcsim", "uuid": "{247b5408-ae91-4e3c-b2f9-a21994658d11}"}, "title": "Atlas URDF and SDF collision geometries vastly different"}, "content": {"raw": "Hi @Stefan_Kohlbrecher , I can work on the rviz issue.  Can you add a link [there](https://github.com/ros-visualization/rviz/issues/633) to a URDF file that shows the problem?  It would make it much easier to test the fix.\n\nThanks.", "markup": "markdown", "html": "<p>Hi @Stefan_Kohlbrecher , I can work on the rviz issue.  Can you add a link <a data-is-external-link=\"true\" href=\"https://github.com/ros-visualization/rviz/issues/633\" rel=\"nofollow\">there</a> to a URDF file that shows the problem?  It would make it much easier to test the fix.</p>\n<p>Thanks.</p>", "type": "rendered"}, "created_on": "2013-05-07T16:56:48.538873+00:00", "user": {"display_name": "Dave Hershberger", "uuid": "{9a3c932f-3319-4ead-9d15-d3ae40f6c321}", "links": {"self": {"href": "https://api.bitbucket.org/2.0/users/%7B9a3c932f-3319-4ead-9d15-d3ae40f6c321%7D"}, "html": {"href": "https://bitbucket.org/%7B9a3c932f-3319-4ead-9d15-d3ae40f6c321%7D/"}, "avatar": {"href": "https://bitbucket.org/account/hershatwillow/avatar/"}}, "nickname": "hershatwillow", "type": "user", "account_id": null}, "updated_on": null, "type": "issue_comment", "id": 3990848}, {"links": {"self": {"href": "data/repositories/osrf/drcsim/issues/255/comments/3991491.json"}, "html": {"href": "#!/osrf/drcsim/issues/255#comment-3991491"}}, "issue": {"links": {"self": {"href": "data/repositories/osrf/drcsim/issues/255.json"}}, "type": "issue", "id": 255, "repository": {"links": {"self": {"href": "data/repositories/osrf/drcsim.json"}, "html": {"href": "#!/osrf/drcsim"}, "avatar": {"href": "data/bytebucket.org/ravatar/{247b5408-ae91-4e3c-b2f9-a21994658d11}ts=c_plus_plus"}}, "type": "repository", "name": "drcsim", "full_name": "osrf/drcsim", "uuid": "{247b5408-ae91-4e3c-b2f9-a21994658d11}"}, "title": "Atlas URDF and SDF collision geometries vastly different"}, "content": {"raw": null, "markup": "markdown", "html": "", "type": "rendered"}, "created_on": "2013-05-07T18:01:59.151624+00:00", "user": {"display_name": "John Hsu", "uuid": "{0a186eae-abf0-4514-a951-23db5eccc286}", "links": {"self": {"href": "https://api.bitbucket.org/2.0/users/%7B0a186eae-abf0-4514-a951-23db5eccc286%7D"}, "html": {"href": "https://bitbucket.org/%7B0a186eae-abf0-4514-a951-23db5eccc286%7D/"}, "avatar": {"href": "https://avatar-management--avatars.us-west-2.prod.public.atl-paas.net/557058:f3968cd3-4910-4384-8349-482a6c7889ec/5445ce6e-6273-47f0-84eb-621c86ca11cb/128"}}, "nickname": "hsu", "type": "user", "account_id": "557058:f3968cd3-4910-4384-8349-482a6c7889ec"}, "updated_on": null, "type": "issue_comment", "id": 3991491}], "page": 1, "size": 7}