{"pagelen": 50, "values": [{"update": {"description": "Quick parameter to reuse the software in arenas", "title": "Scoring testing: allow rosparam as LOGDIR", "destination": {"commit": {"hash": "7ff98f19eb2c", "type": "commit", "links": {"self": {"href": "data/repositories/osrf/drcsim/commit/7ff98f19eb2c.json"}, "html": {"href": "#!/osrf/drcsim/commits/7ff98f19eb2c"}}}, "repository": {"links": {"self": {"href": "data/repositories/osrf/drcsim.json"}, "html": {"href": "#!/osrf/drcsim"}, "avatar": {"href": "data/bytebucket.org/ravatar/{247b5408-ae91-4e3c-b2f9-a21994658d11}ts=c_plus_plus"}}, "type": "repository", "name": "drcsim", "full_name": "osrf/drcsim", "uuid": "{247b5408-ae91-4e3c-b2f9-a21994658d11}"}, "branch": {"name": "default"}}, "reason": "rebase to drcsim_2.6", "source": {"commit": {"hash": "eb551c759c1e", "type": "commit", "links": {"self": {"href": "data/repositories/osrf/drcsim/commit/eb551c759c1e.json"}, "html": {"href": "#!/osrf/drcsim/commits/eb551c759c1e"}}}, "repository": {"links": {"self": {"href": "data/repositories/osrf/drcsim.json"}, "html": {"href": "#!/osrf/drcsim"}, "avatar": {"href": "data/bytebucket.org/ravatar/{247b5408-ae91-4e3c-b2f9-a21994658d11}ts=c_plus_plus"}}, "type": "repository", "name": "drcsim", "full_name": "osrf/drcsim", "uuid": "{247b5408-ae91-4e3c-b2f9-a21994658d11}"}, "branch": {"name": "scoring_param_logfile"}}, "state": "DECLINED", "author": {"display_name": "Jose Luis Rivero", "uuid": "{d12309b2-f745-42ee-b119-aec4fcdf81fe}", "links": {"self": {"href": "https://api.bitbucket.org/2.0/users/%7Bd12309b2-f745-42ee-b119-aec4fcdf81fe%7D"}, "html": {"href": "https://bitbucket.org/%7Bd12309b2-f745-42ee-b119-aec4fcdf81fe%7D/"}, "avatar": {"href": "data/secure.gravatar.com/avatar/109284c8b83411dbc7492138f6167e9ed=httpsavatar-management--avatars.us-west-2.prod.public.atl-paas.netinitialsJR-5.png"}}, "nickname": "Jose Luis Rivero", "type": "user", "account_id": "557058:155a32e2-420c-4d50-98e0-0e722f63f906"}, "date": "2013-05-22T22:09:14.448414+00:00"}, "pull_request": {"type": "pullrequest", "id": 320, "links": {"self": {"href": "data/repositories/osrf/drcsim/pullrequests/320.json"}, "html": {"href": "#!/osrf/drcsim/pull-requests/320"}}, "title": "Scoring testing: allow rosparam as LOGDIR"}}, {"comment": {"links": {"self": {"href": "data/repositories/osrf/drcsim/pullrequests/320/comments/266822.json"}, "html": {"href": "#!/osrf/drcsim/pull-requests/320/_/diff#comment-266822"}}, "parent": {"id": 266821, "links": {"self": {"href": "data/repositories/osrf/drcsim/pullrequests/320/comments/266821.json"}, "html": {"href": "#!/osrf/drcsim/pull-requests/320/_/diff#comment-266821"}}}, "deleted": false, "pullrequest": {"type": "pullrequest", "id": 320, "links": {"self": {"href": "data/repositories/osrf/drcsim/pullrequests/320.json"}, "html": {"href": "#!/osrf/drcsim/pull-requests/320"}}, "title": "Scoring testing: allow rosparam as LOGDIR"}, "content": {"raw": "messing with this, yes. Will redo it against 2.6.", "markup": "markdown", "html": "<p>messing with this, yes. Will redo it against 2.6.</p>", "type": "rendered"}, "created_on": "2013-05-22T22:09:04.931747+00:00", "user": {"display_name": "Jose Luis Rivero", "uuid": "{d12309b2-f745-42ee-b119-aec4fcdf81fe}", "links": {"self": {"href": "https://api.bitbucket.org/2.0/users/%7Bd12309b2-f745-42ee-b119-aec4fcdf81fe%7D"}, "html": {"href": "https://bitbucket.org/%7Bd12309b2-f745-42ee-b119-aec4fcdf81fe%7D/"}, "avatar": {"href": "data/secure.gravatar.com/avatar/109284c8b83411dbc7492138f6167e9ed=httpsavatar-management--avatars.us-west-2.prod.public.atl-paas.netinitialsJR-5.png"}}, "nickname": "Jose Luis Rivero", "type": "user", "account_id": "557058:155a32e2-420c-4d50-98e0-0e722f63f906"}, "updated_on": "2013-05-22T22:09:04.940871+00:00", "type": "pullrequest_comment", "id": 266822}, "pull_request": {"type": "pullrequest", "id": 320, "links": {"self": {"href": "data/repositories/osrf/drcsim/pullrequests/320.json"}, "html": {"href": "#!/osrf/drcsim/pull-requests/320"}}, "title": "Scoring testing: allow rosparam as LOGDIR"}}, {"comment": {"links": {"self": {"href": "data/repositories/osrf/drcsim/pullrequests/320/comments/266821.json"}, "html": {"href": "#!/osrf/drcsim/pull-requests/320/_/diff#comment-266821"}}, "deleted": false, "pullrequest": {"type": "pullrequest", "id": 320, "links": {"self": {"href": "data/repositories/osrf/drcsim/pullrequests/320.json"}, "html": {"href": "#!/osrf/drcsim/pull-requests/320"}}, "title": "Scoring testing: allow rosparam as LOGDIR"}, "content": {"raw": "Target  to 2.6?", "markup": "markdown", "html": "<p>Target  to 2.6?</p>", "type": "rendered"}, "created_on": "2013-05-22T22:08:27.331902+00:00", "user": {"display_name": "Steve Peters", "uuid": "{2ccfed09-18b8-4921-8d58-15ef01092802}", "links": {"self": {"href": "https://api.bitbucket.org/2.0/users/%7B2ccfed09-18b8-4921-8d58-15ef01092802%7D"}, "html": {"href": "https://bitbucket.org/%7B2ccfed09-18b8-4921-8d58-15ef01092802%7D/"}, "avatar": {"href": "data/secure.gravatar.com/avatar/1fb4816dad9e68337d3096f750951f6cd=httpsavatar-management--avatars.us-west-2.prod.public.atl-paas.netinitialsSP-1.png"}}, "nickname": "Steven Peters", "type": "user", "account_id": "557058:5de38267-b118-494c-aa76-4fab35448816"}, "updated_on": "2013-05-22T22:08:27.339134+00:00", "type": "pullrequest_comment", "id": 266821}, "pull_request": {"type": "pullrequest", "id": 320, "links": {"self": {"href": "data/repositories/osrf/drcsim/pullrequests/320.json"}, "html": {"href": "#!/osrf/drcsim/pull-requests/320"}}, "title": "Scoring testing: allow rosparam as LOGDIR"}}, {"update": {"description": "Quick parameter to reuse the software in arenas", "title": "Scoring testing: allow rosparam as LOGDIR", "destination": {"commit": {"hash": "7ff98f19eb2c", "type": "commit", "links": {"self": {"href": "data/repositories/osrf/drcsim/commit/7ff98f19eb2c.json"}, "html": {"href": "#!/osrf/drcsim/commits/7ff98f19eb2c"}}}, "repository": {"links": {"self": {"href": "data/repositories/osrf/drcsim.json"}, "html": {"href": "#!/osrf/drcsim"}, "avatar": {"href": "data/bytebucket.org/ravatar/{247b5408-ae91-4e3c-b2f9-a21994658d11}ts=c_plus_plus"}}, "type": "repository", "name": "drcsim", "full_name": "osrf/drcsim", "uuid": "{247b5408-ae91-4e3c-b2f9-a21994658d11}"}, "branch": {"name": "default"}}, "reason": "", "source": {"commit": {"hash": "eb551c759c1e", "type": "commit", "links": {"self": {"href": "data/repositories/osrf/drcsim/commit/eb551c759c1e.json"}, "html": {"href": "#!/osrf/drcsim/commits/eb551c759c1e"}}}, "repository": {"links": {"self": {"href": "data/repositories/osrf/drcsim.json"}, "html": {"href": "#!/osrf/drcsim"}, "avatar": {"href": "data/bytebucket.org/ravatar/{247b5408-ae91-4e3c-b2f9-a21994658d11}ts=c_plus_plus"}}, "type": "repository", "name": "drcsim", "full_name": "osrf/drcsim", "uuid": "{247b5408-ae91-4e3c-b2f9-a21994658d11}"}, "branch": {"name": "scoring_param_logfile"}}, "state": "OPEN", "author": {"display_name": "Jose Luis Rivero", "uuid": "{d12309b2-f745-42ee-b119-aec4fcdf81fe}", "links": {"self": {"href": "https://api.bitbucket.org/2.0/users/%7Bd12309b2-f745-42ee-b119-aec4fcdf81fe%7D"}, "html": {"href": "https://bitbucket.org/%7Bd12309b2-f745-42ee-b119-aec4fcdf81fe%7D/"}, "avatar": {"href": "data/secure.gravatar.com/avatar/109284c8b83411dbc7492138f6167e9ed=httpsavatar-management--avatars.us-west-2.prod.public.atl-paas.netinitialsJR-5.png"}}, "nickname": "Jose Luis Rivero", "type": "user", "account_id": "557058:155a32e2-420c-4d50-98e0-0e722f63f906"}, "date": "2013-05-22T22:07:06.567901+00:00"}, "pull_request": {"type": "pullrequest", "id": 320, "links": {"self": {"href": "data/repositories/osrf/drcsim/pullrequests/320.json"}, "html": {"href": "#!/osrf/drcsim/pull-requests/320"}}, "title": "Scoring testing: allow rosparam as LOGDIR"}}, {"update": {"description": "Quick parameter to reuse the software in arenas", "title": "Scoring testing: allow rosparam as LOGDIR", "destination": {"commit": {"hash": "7ff98f19eb2c", "type": "commit", "links": {"self": {"href": "data/repositories/osrf/drcsim/commit/7ff98f19eb2c.json"}, "html": {"href": "#!/osrf/drcsim/commits/7ff98f19eb2c"}}}, "repository": {"links": {"self": {"href": "data/repositories/osrf/drcsim.json"}, "html": {"href": "#!/osrf/drcsim"}, "avatar": {"href": "data/bytebucket.org/ravatar/{247b5408-ae91-4e3c-b2f9-a21994658d11}ts=c_plus_plus"}}, "type": "repository", "name": "drcsim", "full_name": "osrf/drcsim", "uuid": "{247b5408-ae91-4e3c-b2f9-a21994658d11}"}, "branch": {"name": "default"}}, "reason": "", "source": {"commit": {"hash": "e9e643b67628", "type": "commit", "links": {"self": {"href": "data/repositories/osrf/drcsim/commit/e9e643b67628.json"}, "html": {"href": "#!/osrf/drcsim/commits/e9e643b67628"}}}, "repository": {"links": {"self": {"href": "data/repositories/osrf/drcsim.json"}, "html": {"href": "#!/osrf/drcsim"}, "avatar": {"href": "data/bytebucket.org/ravatar/{247b5408-ae91-4e3c-b2f9-a21994658d11}ts=c_plus_plus"}}, "type": "repository", "name": "drcsim", "full_name": "osrf/drcsim", "uuid": "{247b5408-ae91-4e3c-b2f9-a21994658d11}"}, "branch": {"name": "scoring_param_logfile"}}, "state": "OPEN", "author": {"display_name": "Jose Luis Rivero", "uuid": "{d12309b2-f745-42ee-b119-aec4fcdf81fe}", "links": {"self": {"href": "https://api.bitbucket.org/2.0/users/%7Bd12309b2-f745-42ee-b119-aec4fcdf81fe%7D"}, "html": {"href": "https://bitbucket.org/%7Bd12309b2-f745-42ee-b119-aec4fcdf81fe%7D/"}, "avatar": {"href": "data/secure.gravatar.com/avatar/109284c8b83411dbc7492138f6167e9ed=httpsavatar-management--avatars.us-west-2.prod.public.atl-paas.netinitialsJR-5.png"}}, "nickname": "Jose Luis Rivero", "type": "user", "account_id": "557058:155a32e2-420c-4d50-98e0-0e722f63f906"}, "date": "2013-05-22T22:05:13.661474+00:00"}, "pull_request": {"type": "pullrequest", "id": 320, "links": {"self": {"href": "data/repositories/osrf/drcsim/pullrequests/320.json"}, "html": {"href": "#!/osrf/drcsim/pull-requests/320"}}, "title": "Scoring testing: allow rosparam as LOGDIR"}}, {"update": {"description": "Quick parameter to reuse the software in arenas", "title": "Scoring testing: allow rosparam as LOGDIR", "destination": {"commit": {"hash": "7ff98f19eb2c", "type": "commit", "links": {"self": {"href": "data/repositories/osrf/drcsim/commit/7ff98f19eb2c.json"}, "html": {"href": "#!/osrf/drcsim/commits/7ff98f19eb2c"}}}, "repository": {"links": {"self": {"href": "data/repositories/osrf/drcsim.json"}, "html": {"href": "#!/osrf/drcsim"}, "avatar": {"href": "data/bytebucket.org/ravatar/{247b5408-ae91-4e3c-b2f9-a21994658d11}ts=c_plus_plus"}}, "type": "repository", "name": "drcsim", "full_name": "osrf/drcsim", "uuid": "{247b5408-ae91-4e3c-b2f9-a21994658d11}"}, "branch": {"name": "default"}}, "reason": "", "source": {"commit": {"hash": "e9e643b67628", "type": "commit", "links": {"self": {"href": "data/repositories/osrf/drcsim/commit/e9e643b67628.json"}, "html": {"href": "#!/osrf/drcsim/commits/e9e643b67628"}}}, "repository": {"links": {"self": {"href": "data/repositories/osrf/drcsim.json"}, "html": {"href": "#!/osrf/drcsim"}, "avatar": {"href": "data/bytebucket.org/ravatar/{247b5408-ae91-4e3c-b2f9-a21994658d11}ts=c_plus_plus"}}, "type": "repository", "name": "drcsim", "full_name": "osrf/drcsim", "uuid": "{247b5408-ae91-4e3c-b2f9-a21994658d11}"}, "branch": {"name": "scoring_param_logfile"}}, "state": "OPEN", "author": {"display_name": "Jose Luis Rivero", "uuid": "{d12309b2-f745-42ee-b119-aec4fcdf81fe}", "links": {"self": {"href": "https://api.bitbucket.org/2.0/users/%7Bd12309b2-f745-42ee-b119-aec4fcdf81fe%7D"}, "html": {"href": "https://bitbucket.org/%7Bd12309b2-f745-42ee-b119-aec4fcdf81fe%7D/"}, "avatar": {"href": "data/secure.gravatar.com/avatar/109284c8b83411dbc7492138f6167e9ed=httpsavatar-management--avatars.us-west-2.prod.public.atl-paas.netinitialsJR-5.png"}}, "nickname": "Jose Luis Rivero", "type": "user", "account_id": "557058:155a32e2-420c-4d50-98e0-0e722f63f906"}, "date": "2013-05-22T22:05:13.610096+00:00"}, "pull_request": {"type": "pullrequest", "id": 320, "links": {"self": {"href": "data/repositories/osrf/drcsim/pullrequests/320.json"}, "html": {"href": "#!/osrf/drcsim/pull-requests/320"}}, "title": "Scoring testing: allow rosparam as LOGDIR"}}]}