{"links": {"self": {"href": "data/repositories/osrf/drcsim/pullrequests/144/comments/145449.json"}, "html": {"href": "#!/osrf/drcsim/pull-requests/144/_/diff#comment-145449"}}, "parent": {"id": 145422, "links": {"self": {"href": "data/repositories/osrf/drcsim/pullrequests/144/comments/145422.json"}, "html": {"href": "#!/osrf/drcsim/pull-requests/144/_/diff#comment-145422"}}}, "deleted": false, "pullrequest": {"type": "pullrequest", "id": 144, "links": {"self": {"href": "data/repositories/osrf/drcsim/pullrequests/144.json"}, "html": {"href": "#!/osrf/drcsim/pull-requests/144"}}, "title": "Three VRC worlds"}, "content": {"raw": "yep, driving along the road with the robot sitting inside works for me.", "markup": "markdown", "html": "<p>yep, driving along the road with the robot sitting inside works for me.</p>", "type": "rendered"}, "created_on": "2013-03-07T22:38:45.191013+00:00", "user": {"display_name": "Thomas Koletschka", "uuid": "{b33092ac-6376-48d1-9803-d9e6de445d1a}", "links": {"self": {"href": "https://api.bitbucket.org/2.0/users/%7Bb33092ac-6376-48d1-9803-d9e6de445d1a%7D"}, "html": {"href": "https://bitbucket.org/%7Bb33092ac-6376-48d1-9803-d9e6de445d1a%7D/"}, "avatar": {"href": "https://bitbucket.org/account/thomasko/avatar/"}}, "nickname": "thomasko", "type": "user", "account_id": null}, "updated_on": "2013-03-07T22:38:45.288416+00:00", "type": "pullrequest_comment", "id": 145449}