{"pagelen": 100, "values": [{"links": {"self": {"href": "data/repositories/osrf/drcsim/issues/60/comments/2593312.json"}, "html": {"href": "#!/osrf/drcsim/issues/60#comment-2593312"}}, "issue": {"links": {"self": {"href": "data/repositories/osrf/drcsim/issues/60.json"}}, "type": "issue", "id": 60, "repository": {"links": {"self": {"href": "data/repositories/osrf/drcsim.json"}, "html": {"href": "#!/osrf/drcsim"}, "avatar": {"href": "data/bytebucket.org/ravatar/{247b5408-ae91-4e3c-b2f9-a21994658d11}ts=c_plus_plus"}}, "type": "repository", "name": "drcsim", "full_name": "osrf/drcsim", "uuid": "{247b5408-ae91-4e3c-b2f9-a21994658d11}"}, "title": "standpipe rotates back"}, "content": {"raw": "standpipe is fixed to the world by [a joint](#!/osrf/drcsim/src/9b1ffdd0fe60a8a314ed72ab154678f022f09f56/models/standpipe/model.sdf?at=default#cl-61), if you want to move it you have to change the [link pose](#!/osrf/drcsim/src/9b1ffdd0fe60a8a314ed72ab154678f022f09f56/models/standpipe/model.sdf?at=default#cl-5).", "markup": "markdown", "html": "<p>standpipe is fixed to the world by <a data-is-external-link=\"true\" href=\"#!/osrf/drcsim/src/9b1ffdd0fe60a8a314ed72ab154678f022f09f56/models/standpipe/model.sdf?at=default#cl-61\" rel=\"nofollow\">a joint</a>, if you want to move it you have to change the <a data-is-external-link=\"true\" href=\"#!/osrf/drcsim/src/9b1ffdd0fe60a8a314ed72ab154678f022f09f56/models/standpipe/model.sdf?at=default#cl-5\" rel=\"nofollow\">link pose</a>.</p>", "type": "rendered"}, "created_on": "2012-12-11T00:40:42.633186+00:00", "user": {"display_name": "John Hsu", "uuid": "{0a186eae-abf0-4514-a951-23db5eccc286}", "links": {"self": {"href": "https://api.bitbucket.org/2.0/users/%7B0a186eae-abf0-4514-a951-23db5eccc286%7D"}, "html": {"href": "https://bitbucket.org/%7B0a186eae-abf0-4514-a951-23db5eccc286%7D/"}, "avatar": {"href": "https://avatar-management--avatars.us-west-2.prod.public.atl-paas.net/557058:f3968cd3-4910-4384-8349-482a6c7889ec/5445ce6e-6273-47f0-84eb-621c86ca11cb/128"}}, "nickname": "hsu", "type": "user", "account_id": "557058:f3968cd3-4910-4384-8349-482a6c7889ec"}, "updated_on": null, "type": "issue_comment", "id": 2593312}, {"links": {"self": {"href": "data/repositories/osrf/drcsim/issues/60/comments/2593318.json"}, "html": {"href": "#!/osrf/drcsim/issues/60#comment-2593318"}}, "issue": {"links": {"self": {"href": "data/repositories/osrf/drcsim/issues/60.json"}}, "type": "issue", "id": 60, "repository": {"links": {"self": {"href": "data/repositories/osrf/drcsim.json"}, "html": {"href": "#!/osrf/drcsim"}, "avatar": {"href": "data/bytebucket.org/ravatar/{247b5408-ae91-4e3c-b2f9-a21994658d11}ts=c_plus_plus"}}, "type": "repository", "name": "drcsim", "full_name": "osrf/drcsim", "uuid": "{247b5408-ae91-4e3c-b2f9-a21994658d11}"}, "title": "standpipe rotates back"}, "content": {"raw": "Why isn't it a static object instead of linking it to /world? Or is this required for hose coupling?", "markup": "markdown", "html": "<p>Why isn't it a static object instead of linking it to /world? Or is this required for hose coupling?</p>", "type": "rendered"}, "created_on": "2012-12-11T00:42:23.232080+00:00", "user": {"display_name": "Thomas Koletschka", "uuid": "{b33092ac-6376-48d1-9803-d9e6de445d1a}", "links": {"self": {"href": "https://api.bitbucket.org/2.0/users/%7Bb33092ac-6376-48d1-9803-d9e6de445d1a%7D"}, "html": {"href": "https://bitbucket.org/%7Bb33092ac-6376-48d1-9803-d9e6de445d1a%7D/"}, "avatar": {"href": "https://bitbucket.org/account/thomasko/avatar/"}}, "nickname": "thomasko", "type": "user", "account_id": null}, "updated_on": null, "type": "issue_comment", "id": 2593318}, {"links": {"self": {"href": "data/repositories/osrf/drcsim/issues/60/comments/2600114.json"}, "html": {"href": "#!/osrf/drcsim/issues/60#comment-2600114"}}, "issue": {"links": {"self": {"href": "data/repositories/osrf/drcsim/issues/60.json"}}, "type": "issue", "id": 60, "repository": {"links": {"self": {"href": "data/repositories/osrf/drcsim.json"}, "html": {"href": "#!/osrf/drcsim"}, "avatar": {"href": "data/bytebucket.org/ravatar/{247b5408-ae91-4e3c-b2f9-a21994658d11}ts=c_plus_plus"}}, "type": "repository", "name": "drcsim", "full_name": "osrf/drcsim", "uuid": "{247b5408-ae91-4e3c-b2f9-a21994658d11}"}, "title": "standpipe rotates back"}, "content": {"raw": "We currently have it connected to the world to ensure that the hose coupling will work. It may be possible to use a static object, but we haven't tested that.", "markup": "markdown", "html": "<p>We currently have it connected to the world to ensure that the hose coupling will work. It may be possible to use a static object, but we haven't tested that.</p>", "type": "rendered"}, "created_on": "2012-12-11T18:15:59.827875+00:00", "user": {"display_name": "Steve Peters", "uuid": "{2ccfed09-18b8-4921-8d58-15ef01092802}", "links": {"self": {"href": "https://api.bitbucket.org/2.0/users/%7B2ccfed09-18b8-4921-8d58-15ef01092802%7D"}, "html": {"href": "https://bitbucket.org/%7B2ccfed09-18b8-4921-8d58-15ef01092802%7D/"}, "avatar": {"href": "data/secure.gravatar.com/avatar/1fb4816dad9e68337d3096f750951f6cd=httpsavatar-management--avatars.us-west-2.prod.public.atl-paas.netinitialsSP-1.png"}}, "nickname": "Steven Peters", "type": "user", "account_id": "557058:5de38267-b118-494c-aa76-4fab35448816"}, "updated_on": null, "type": "issue_comment", "id": 2600114}, {"links": {"self": {"href": "data/repositories/osrf/drcsim/issues/60/comments/2600122.json"}, "html": {"href": "#!/osrf/drcsim/issues/60#comment-2600122"}}, "issue": {"links": {"self": {"href": "data/repositories/osrf/drcsim/issues/60.json"}}, "type": "issue", "id": 60, "repository": {"links": {"self": {"href": "data/repositories/osrf/drcsim.json"}, "html": {"href": "#!/osrf/drcsim"}, "avatar": {"href": "data/bytebucket.org/ravatar/{247b5408-ae91-4e3c-b2f9-a21994658d11}ts=c_plus_plus"}}, "type": "repository", "name": "drcsim", "full_name": "osrf/drcsim", "uuid": "{247b5408-ae91-4e3c-b2f9-a21994658d11}"}, "title": "standpipe rotates back"}, "content": {"raw": "Default standpipe cannot rotate because it is connected to world by a fixed joint. Edit the sdf to change its pose.", "markup": "markdown", "html": "<p>Default standpipe cannot rotate because it is connected to world by a fixed joint. Edit the sdf to change its pose.</p>", "type": "rendered"}, "created_on": "2012-12-11T18:17:00.958530+00:00", "user": {"display_name": "Steve Peters", "uuid": "{2ccfed09-18b8-4921-8d58-15ef01092802}", "links": {"self": {"href": "https://api.bitbucket.org/2.0/users/%7B2ccfed09-18b8-4921-8d58-15ef01092802%7D"}, "html": {"href": "https://bitbucket.org/%7B2ccfed09-18b8-4921-8d58-15ef01092802%7D/"}, "avatar": {"href": "data/secure.gravatar.com/avatar/1fb4816dad9e68337d3096f750951f6cd=httpsavatar-management--avatars.us-west-2.prod.public.atl-paas.netinitialsSP-1.png"}}, "nickname": "Steven Peters", "type": "user", "account_id": "557058:5de38267-b118-494c-aa76-4fab35448816"}, "updated_on": null, "type": "issue_comment", "id": 2600122}], "page": 1, "size": 4}