{"links": {"self": {"href": "data/repositories/osrf/drcsim/issues/227/comments/3921190.json"}, "html": {"href": "#!/osrf/drcsim/issues/227#comment-3921190"}}, "issue": {"links": {"self": {"href": "data/repositories/osrf/drcsim/issues/227.json"}}, "type": "issue", "id": 227, "repository": {"links": {"self": {"href": "data/repositories/osrf/drcsim.json"}, "html": {"href": "#!/osrf/drcsim"}, "avatar": {"href": "data/bytebucket.org/ravatar/{247b5408-ae91-4e3c-b2f9-a21994658d11}ts=c_plus_plus"}}, "type": "repository", "name": "drcsim", "full_name": "osrf/drcsim", "uuid": "{247b5408-ae91-4e3c-b2f9-a21994658d11}"}, "title": "QuadProgPP required to link actionlib_server"}, "content": {"raw": "Hi Mr. Rivero,\n\nThanks for your help and sorry for not providing the complete info before. Here the details:\n\n* drcsim info: drcsim_2.5 branch\n* Modified the code? : Not at all\n* gcc version: 4.7\n* ROS version: Groovy\n* System: Ubuntu 12.10, 64 bits\n* Gazebo version: 1.8.0\n* boost: 1.49\n\nThe terminal output is [here](http://pastebin.com/TE8ypsSA) and the CMakeOutput log is [here](http://pastebin.com/NW5NRv1T). \n\nThanks again!\n\n", "markup": "markdown", "html": "<p>Hi Mr. Rivero,</p>\n<p>Thanks for your help and sorry for not providing the complete info before. Here the details:</p>\n<ul>\n<li>drcsim info: drcsim_2.5 branch</li>\n<li>Modified the code? : Not at all</li>\n<li>gcc version: 4.7</li>\n<li>ROS version: Groovy</li>\n<li>System: Ubuntu 12.10, 64 bits</li>\n<li>Gazebo version: 1.8.0</li>\n<li>boost: 1.49</li>\n</ul>\n<p>The terminal output is <a data-is-external-link=\"true\" href=\"http://pastebin.com/TE8ypsSA\" rel=\"nofollow\">here</a> and the CMakeOutput log is <a data-is-external-link=\"true\" href=\"http://pastebin.com/NW5NRv1T\" rel=\"nofollow\">here</a>. </p>\n<p>Thanks again!</p>", "type": "rendered"}, "created_on": "2013-04-30T15:30:40.770378+00:00", "user": {"display_name": "Ana Huaman", "uuid": "{fb8c4958-55c6-4434-b84f-c21665c0caf6}", "links": {"self": {"href": "https://api.bitbucket.org/2.0/users/%7Bfb8c4958-55c6-4434-b84f-c21665c0caf6%7D"}, "html": {"href": "https://bitbucket.org/%7Bfb8c4958-55c6-4434-b84f-c21665c0caf6%7D/"}, "avatar": {"href": "data/secure.gravatar.com/avatar/64be5ea887d4e35aeb989a78263cd5d7d=httpsavatar-management--avatars.us-west-2.prod.public.atl-paas.netinitialsAH-6.png"}}, "nickname": "ana-GT", "type": "user", "account_id": "557058:7f4ac918-037c-4930-bed5-5c119167b1bb"}, "updated_on": "2013-04-30T15:31:55.761236+00:00", "type": "issue_comment", "id": 3921190}