{"pagelen": 100, "values": [{"links": {"self": {"href": "data/repositories/osrf/drcsim/issues/425/comments/12380439.json"}, "html": {"href": "#!/osrf/drcsim/issues/425#comment-12380439"}}, "issue": {"links": {"self": {"href": "data/repositories/osrf/drcsim/issues/425.json"}}, "type": "issue", "id": 425, "repository": {"links": {"self": {"href": "data/repositories/osrf/drcsim.json"}, "html": {"href": "#!/osrf/drcsim"}, "avatar": {"href": "data/bytebucket.org/ravatar/{247b5408-ae91-4e3c-b2f9-a21994658d11}ts=c_plus_plus"}}, "type": "repository", "name": "drcsim", "full_name": "osrf/drcsim", "uuid": "{247b5408-ae91-4e3c-b2f9-a21994658d11}"}, "title": "Topic names - some minor corrections"}, "content": {"raw": null, "markup": "markdown", "html": "", "type": "rendered"}, "created_on": "2014-09-16T15:46:46.371042+00:00", "user": {"display_name": "Nate Koenig", "uuid": "{c862cdd9-fcc8-4419-9fc7-e20db14b8fcb}", "links": {"self": {"href": "https://api.bitbucket.org/2.0/users/%7Bc862cdd9-fcc8-4419-9fc7-e20db14b8fcb%7D"}, "html": {"href": "https://bitbucket.org/%7Bc862cdd9-fcc8-4419-9fc7-e20db14b8fcb%7D/"}, "avatar": {"href": "https://avatar-management--avatars.us-west-2.prod.public.atl-paas.net/557058:095b1e12-74ed-4e20-b44f-2f0745b616e0/ca24bb11-4787-4b14-a20d-d91835e9bde2/128"}}, "nickname": "Nathan Koenig", "type": "user", "account_id": "557058:095b1e12-74ed-4e20-b44f-2f0745b616e0"}, "updated_on": null, "type": "issue_comment", "id": 12380439}, {"links": {"self": {"href": "data/repositories/osrf/drcsim/issues/425/comments/12403645.json"}, "html": {"href": "#!/osrf/drcsim/issues/425#comment-12403645"}}, "issue": {"links": {"self": {"href": "data/repositories/osrf/drcsim/issues/425.json"}}, "type": "issue", "id": 425, "repository": {"links": {"self": {"href": "data/repositories/osrf/drcsim.json"}, "html": {"href": "#!/osrf/drcsim"}, "avatar": {"href": "data/bytebucket.org/ravatar/{247b5408-ae91-4e3c-b2f9-a21994658d11}ts=c_plus_plus"}}, "type": "repository", "name": "drcsim", "full_name": "osrf/drcsim", "uuid": "{247b5408-ae91-4e3c-b2f9-a21994658d11}"}, "title": "Topic names - some minor corrections"}, "content": {"raw": "thanks! please see pull request #463", "markup": "markdown", "html": "<p>thanks! please see <a href=\"#!/osrf/drcsim/pull-requests/463/fix-isue-425-launch-files\" rel=\"nofollow\" class=\"ap-connect-link\">pull request #463</a></p>", "type": "rendered"}, "created_on": "2014-09-17T15:36:56.564609+00:00", "user": {"display_name": "John Hsu", "uuid": "{0a186eae-abf0-4514-a951-23db5eccc286}", "links": {"self": {"href": "https://api.bitbucket.org/2.0/users/%7B0a186eae-abf0-4514-a951-23db5eccc286%7D"}, "html": {"href": "https://bitbucket.org/%7B0a186eae-abf0-4514-a951-23db5eccc286%7D/"}, "avatar": {"href": "https://avatar-management--avatars.us-west-2.prod.public.atl-paas.net/557058:f3968cd3-4910-4384-8349-482a6c7889ec/5445ce6e-6273-47f0-84eb-621c86ca11cb/128"}}, "nickname": "hsu", "type": "user", "account_id": "557058:f3968cd3-4910-4384-8349-482a6c7889ec"}, "updated_on": null, "type": "issue_comment", "id": 12403645}, {"links": {"self": {"href": "data/repositories/osrf/drcsim/issues/425/comments/12406851.json"}, "html": {"href": "#!/osrf/drcsim/issues/425#comment-12406851"}}, "issue": {"links": {"self": {"href": "data/repositories/osrf/drcsim/issues/425.json"}}, "type": "issue", "id": 425, "repository": {"links": {"self": {"href": "data/repositories/osrf/drcsim.json"}, "html": {"href": "#!/osrf/drcsim"}, "avatar": {"href": "data/bytebucket.org/ravatar/{247b5408-ae91-4e3c-b2f9-a21994658d11}ts=c_plus_plus"}}, "type": "repository", "name": "drcsim", "full_name": "osrf/drcsim", "uuid": "{247b5408-ae91-4e3c-b2f9-a21994658d11}"}, "title": "Topic names - some minor corrections"}, "content": {"raw": "The multisense driver changed a number of names a couple months ago.  I will take a look at #463 and what our current launch files look like to provide feedback by 9/19.", "markup": "markdown", "html": "<p>The multisense driver changed a number of names a couple months ago.  I will take a look at <a href=\"#!/osrf/drcsim/issues/463/building-vrcpluginso-from-source-results\" rel=\"nofollow\" title=\"Building VRCPlugin.so from source results in much larger .so\" class=\"ap-connect-link\"><s>#463</s></a> and what our current launch files look like to provide feedback by 9/19.</p>", "type": "rendered"}, "created_on": "2014-09-17T18:46:59.329319+00:00", "user": {"display_name": "GoRobotGo", "uuid": "{2fd8dac8-286d-461a-b7dd-dba99deea025}", "links": {"self": {"href": "https://api.bitbucket.org/2.0/users/%7B2fd8dac8-286d-461a-b7dd-dba99deea025%7D"}, "html": {"href": "https://bitbucket.org/%7B2fd8dac8-286d-461a-b7dd-dba99deea025%7D/"}, "avatar": {"href": "data/secure.gravatar.com/avatar/6431739b101c18640b5a84d359fdd274d=httpsavatar-management--avatars.us-west-2.prod.public.atl-paas.netinitialsG-4.png"}}, "nickname": "GoRobotGo", "type": "user", "account_id": "557058:44b40072-c04b-41ae-ad09-376db9ebffa1"}, "updated_on": null, "type": "issue_comment", "id": 12406851}, {"links": {"self": {"href": "data/repositories/osrf/drcsim/issues/425/comments/12454814.json"}, "html": {"href": "#!/osrf/drcsim/issues/425#comment-12454814"}}, "issue": {"links": {"self": {"href": "data/repositories/osrf/drcsim/issues/425.json"}}, "type": "issue", "id": 425, "repository": {"links": {"self": {"href": "data/repositories/osrf/drcsim.json"}, "html": {"href": "#!/osrf/drcsim"}, "avatar": {"href": "data/bytebucket.org/ravatar/{247b5408-ae91-4e3c-b2f9-a21994658d11}ts=c_plus_plus"}}, "type": "repository", "name": "drcsim", "full_name": "osrf/drcsim", "uuid": "{247b5408-ae91-4e3c-b2f9-a21994658d11}"}, "title": "Topic names - some minor corrections"}, "content": {"raw": "I looked over #463 and the current hardware topics.   Here are my comments:\nAll of the /multisense_sl are now /multisense    (the _sl is gone)\nThe laser is now on /multisense/lidar_scan and  /multisense/lidar_points2\n\nThanks!", "markup": "markdown", "html": "<p>I looked over <a href=\"#!/osrf/drcsim/issues/463/building-vrcpluginso-from-source-results\" rel=\"nofollow\" title=\"Building VRCPlugin.so from source results in much larger .so\" class=\"ap-connect-link\"><s>#463</s></a> and the current hardware topics.   Here are my comments:\nAll of the /multisense_sl are now /multisense    (the _sl is gone)\nThe laser is now on /multisense/lidar_scan and  /multisense/lidar_points2</p>\n<p>Thanks!</p>", "type": "rendered"}, "created_on": "2014-09-19T22:18:46.773797+00:00", "user": {"display_name": "GoRobotGo", "uuid": "{2fd8dac8-286d-461a-b7dd-dba99deea025}", "links": {"self": {"href": "https://api.bitbucket.org/2.0/users/%7B2fd8dac8-286d-461a-b7dd-dba99deea025%7D"}, "html": {"href": "https://bitbucket.org/%7B2fd8dac8-286d-461a-b7dd-dba99deea025%7D/"}, "avatar": {"href": "data/secure.gravatar.com/avatar/6431739b101c18640b5a84d359fdd274d=httpsavatar-management--avatars.us-west-2.prod.public.atl-paas.netinitialsG-4.png"}}, "nickname": "GoRobotGo", "type": "user", "account_id": "557058:44b40072-c04b-41ae-ad09-376db9ebffa1"}, "updated_on": null, "type": "issue_comment", "id": 12454814}, {"links": {"self": {"href": "data/repositories/osrf/drcsim/issues/425/comments/12455630.json"}, "html": {"href": "#!/osrf/drcsim/issues/425#comment-12455630"}}, "issue": {"links": {"self": {"href": "data/repositories/osrf/drcsim/issues/425.json"}}, "type": "issue", "id": 425, "repository": {"links": {"self": {"href": "data/repositories/osrf/drcsim.json"}, "html": {"href": "#!/osrf/drcsim"}, "avatar": {"href": "data/bytebucket.org/ravatar/{247b5408-ae91-4e3c-b2f9-a21994658d11}ts=c_plus_plus"}}, "type": "repository", "name": "drcsim", "full_name": "osrf/drcsim", "uuid": "{247b5408-ae91-4e3c-b2f9-a21994658d11}"}, "title": "Topic names - some minor corrections"}, "content": {"raw": "updated pull request #463\n\nc2f36d9, 23716ba\n\nplease take a look.\n", "markup": "markdown", "html": "<p>updated <a href=\"#!/osrf/drcsim/pull-requests/463/fix-isue-425-launch-files\" rel=\"nofollow\" class=\"ap-connect-link\">pull request #463</a></p>\n<p><a href=\"#!/osrf/drcsim/commits/c2f36d9\" rel=\"nofollow\" class=\"ap-connect-link\">c2f36d9</a>, <a href=\"#!/osrf/drcsim/commits/23716ba\" rel=\"nofollow\" class=\"ap-connect-link\">23716ba</a></p>\n<p>please take a look.</p>", "type": "rendered"}, "created_on": "2014-09-20T00:20:31.400251+00:00", "user": {"display_name": "John Hsu", "uuid": "{0a186eae-abf0-4514-a951-23db5eccc286}", "links": {"self": {"href": "https://api.bitbucket.org/2.0/users/%7B0a186eae-abf0-4514-a951-23db5eccc286%7D"}, "html": {"href": "https://bitbucket.org/%7B0a186eae-abf0-4514-a951-23db5eccc286%7D/"}, "avatar": {"href": "https://avatar-management--avatars.us-west-2.prod.public.atl-paas.net/557058:f3968cd3-4910-4384-8349-482a6c7889ec/5445ce6e-6273-47f0-84eb-621c86ca11cb/128"}}, "nickname": "hsu", "type": "user", "account_id": "557058:f3968cd3-4910-4384-8349-482a6c7889ec"}, "updated_on": "2014-09-20T00:40:19.406826+00:00", "type": "issue_comment", "id": 12455630}, {"links": {"self": {"href": "data/repositories/osrf/drcsim/issues/425/comments/12456468.json"}, "html": {"href": "#!/osrf/drcsim/issues/425#comment-12456468"}}, "issue": {"links": {"self": {"href": "data/repositories/osrf/drcsim/issues/425.json"}}, "type": "issue", "id": 425, "repository": {"links": {"self": {"href": "data/repositories/osrf/drcsim.json"}, "html": {"href": "#!/osrf/drcsim"}, "avatar": {"href": "data/bytebucket.org/ravatar/{247b5408-ae91-4e3c-b2f9-a21994658d11}ts=c_plus_plus"}}, "type": "repository", "name": "drcsim", "full_name": "osrf/drcsim", "uuid": "{247b5408-ae91-4e3c-b2f9-a21994658d11}"}, "title": "Topic names - some minor corrections"}, "content": {"raw": "Thank you, that looks good.  I added some code review questions to the pull request.", "markup": "markdown", "html": "<p>Thank you, that looks good.  I added some code review questions to the pull request.</p>", "type": "rendered"}, "created_on": "2014-09-20T04:25:15.087048+00:00", "user": {"display_name": "GoRobotGo", "uuid": "{2fd8dac8-286d-461a-b7dd-dba99deea025}", "links": {"self": {"href": "https://api.bitbucket.org/2.0/users/%7B2fd8dac8-286d-461a-b7dd-dba99deea025%7D"}, "html": {"href": "https://bitbucket.org/%7B2fd8dac8-286d-461a-b7dd-dba99deea025%7D/"}, "avatar": {"href": "data/secure.gravatar.com/avatar/6431739b101c18640b5a84d359fdd274d=httpsavatar-management--avatars.us-west-2.prod.public.atl-paas.netinitialsG-4.png"}}, "nickname": "GoRobotGo", "type": "user", "account_id": "557058:44b40072-c04b-41ae-ad09-376db9ebffa1"}, "updated_on": null, "type": "issue_comment", "id": 12456468}, {"links": {"self": {"href": "data/repositories/osrf/drcsim/issues/425/comments/16119880.json"}, "html": {"href": "#!/osrf/drcsim/issues/425#comment-16119880"}}, "issue": {"links": {"self": {"href": "data/repositories/osrf/drcsim/issues/425.json"}}, "type": "issue", "id": 425, "repository": {"links": {"self": {"href": "data/repositories/osrf/drcsim.json"}, "html": {"href": "#!/osrf/drcsim"}, "avatar": {"href": "data/bytebucket.org/ravatar/{247b5408-ae91-4e3c-b2f9-a21994658d11}ts=c_plus_plus"}}, "type": "repository", "name": "drcsim", "full_name": "osrf/drcsim", "uuid": "{247b5408-ae91-4e3c-b2f9-a21994658d11}"}, "title": "Topic names - some minor corrections"}, "content": {"raw": null, "markup": "markdown", "html": "", "type": "rendered"}, "created_on": "2015-03-05T21:31:27.165335+00:00", "user": {"display_name": "John Hsu", "uuid": "{0a186eae-abf0-4514-a951-23db5eccc286}", "links": {"self": {"href": "https://api.bitbucket.org/2.0/users/%7B0a186eae-abf0-4514-a951-23db5eccc286%7D"}, "html": {"href": "https://bitbucket.org/%7B0a186eae-abf0-4514-a951-23db5eccc286%7D/"}, "avatar": {"href": "https://avatar-management--avatars.us-west-2.prod.public.atl-paas.net/557058:f3968cd3-4910-4384-8349-482a6c7889ec/5445ce6e-6273-47f0-84eb-621c86ca11cb/128"}}, "nickname": "hsu", "type": "user", "account_id": "557058:f3968cd3-4910-4384-8349-482a6c7889ec"}, "updated_on": null, "type": "issue_comment", "id": 16119880}], "page": 1, "size": 7}