{"links": {"self": {"href": "data/repositories/osrf/drcsim/issues/476/comments/14974734.json"}, "html": {"href": "#!/osrf/drcsim/issues/476#comment-14974734"}}, "issue": {"links": {"self": {"href": "data/repositories/osrf/drcsim/issues/476.json"}}, "type": "issue", "id": 476, "repository": {"links": {"self": {"href": "data/repositories/osrf/drcsim.json"}, "html": {"href": "#!/osrf/drcsim"}, "avatar": {"href": "data/bytebucket.org/ravatar/{247b5408-ae91-4e3c-b2f9-a21994658d11}ts=c_plus_plus"}}, "type": "repository", "name": "drcsim", "full_name": "osrf/drcsim", "uuid": "{247b5408-ae91-4e3c-b2f9-a21994658d11}"}, "title": "Wobbling in BDI manipulation mode"}, "content": {"raw": "Tried changing physics variable and tested with:\n\n  * ODE with RobotiQ hands with reduced time step 0.3ms and 500 iters\n  * ODE with no hands with reduced time step 0.3ms and 500 iters\n  * DART with no hands\n\nSame wobbling behavior exists.  My conclusion is this is controller induced, not physics solver related.  @BillBlank cc'd for comment.\n\nI tried a few combinations of different joint damping settings, but no magic bullet yet (by tweaking model).\n\nFor reference, my test command is:\n\n~~~\nrostopic pub -1 /atlas/atlas_sim_interface_command atlas_msgs/AtlasSimInterfaceCommand '{behavior: 6, manipulate_params: { use_demo_mode: False, use_desired: True, desired: { pelvis_height: 0.7, pelvis_yaw: 0.0, pelvis_lat: 0.0  } }, k_effort: [ 255, 255, 255, 255, 0, 0, 0, 0, 0, 0, 0, 0, 0, 0, 0, 0, 255, 255, 255, 255, 255, 255, 255, 255, 255, 255, 255, 255] }'\n~~~", "markup": "markdown", "html": "<p>Tried changing physics variable and tested with:</p>\n<ul>\n<li>ODE with RobotiQ hands with reduced time step 0.3ms and 500 iters</li>\n<li>ODE with no hands with reduced time step 0.3ms and 500 iters</li>\n<li>DART with no hands</li>\n</ul>\n<p>Same wobbling behavior exists.  My conclusion is this is controller induced, not physics solver related.  @BillBlank cc'd for comment.</p>\n<p>I tried a few combinations of different joint damping settings, but no magic bullet yet (by tweaking model).</p>\n<p>For reference, my test command is:</p>\n<div class=\"codehilite\"><pre><span></span>rostopic pub -1 /atlas/atlas_sim_interface_command atlas_msgs/AtlasSimInterfaceCommand &#39;{behavior: 6, manipulate_params: { use_demo_mode: False, use_desired: True, desired: { pelvis_height: 0.7, pelvis_yaw: 0.0, pelvis_lat: 0.0  } }, k_effort: [ 255, 255, 255, 255, 0, 0, 0, 0, 0, 0, 0, 0, 0, 0, 0, 0, 255, 255, 255, 255, 255, 255, 255, 255, 255, 255, 255, 255] }&#39;\n</pre></div>", "type": "rendered"}, "created_on": "2015-01-21T00:44:22.866503+00:00", "user": {"display_name": "John Hsu", "uuid": "{0a186eae-abf0-4514-a951-23db5eccc286}", "links": {"self": {"href": "https://api.bitbucket.org/2.0/users/%7B0a186eae-abf0-4514-a951-23db5eccc286%7D"}, "html": {"href": "https://bitbucket.org/%7B0a186eae-abf0-4514-a951-23db5eccc286%7D/"}, "avatar": {"href": "https://avatar-management--avatars.us-west-2.prod.public.atl-paas.net/557058:f3968cd3-4910-4384-8349-482a6c7889ec/5445ce6e-6273-47f0-84eb-621c86ca11cb/128"}}, "nickname": "hsu", "type": "user", "account_id": "557058:f3968cd3-4910-4384-8349-482a6c7889ec"}, "updated_on": "2015-01-21T19:57:42.742182+00:00", "type": "issue_comment", "id": 14974734}