{"priority": "major", "kind": "bug", "repository": {"links": {"self": {"href": "data/repositories/osrf/drcsim.json"}, "html": {"href": "#!/osrf/drcsim"}, "avatar": {"href": "data/bytebucket.org/ravatar/{247b5408-ae91-4e3c-b2f9-a21994658d11}ts=c_plus_plus"}}, "type": "repository", "name": "drcsim", "full_name": "osrf/drcsim", "uuid": "{247b5408-ae91-4e3c-b2f9-a21994658d11}"}, "links": {"attachments": {"href": "data/repositories/osrf/drcsim/issues/225/attachments_page=1.json"}, "self": {"href": "data/repositories/osrf/drcsim/issues/225.json"}, "watch": {"href": "https://api.bitbucket.org/2.0/repositories/osrf/drcsim/issues/225/watch"}, "comments": {"href": "data/repositories/osrf/drcsim/issues/225/comments_page=1.json"}, "html": {"href": "#!/osrf/drcsim/issues/225/atlas-falls-down-at-initialization"}, "vote": {"href": "https://api.bitbucket.org/2.0/repositories/osrf/drcsim/issues/225/vote"}}, "reporter": {"display_name": "Thomas Koletschka", "uuid": "{b33092ac-6376-48d1-9803-d9e6de445d1a}", "links": {"self": {"href": "https://api.bitbucket.org/2.0/users/%7Bb33092ac-6376-48d1-9803-d9e6de445d1a%7D"}, "html": {"href": "https://bitbucket.org/%7Bb33092ac-6376-48d1-9803-d9e6de445d1a%7D/"}, "avatar": {"href": "https://bitbucket.org/account/thomasko/avatar/"}}, "nickname": "thomasko", "type": "user", "account_id": null}, "title": "Atlas falls down at initialization", "component": null, "votes": 0, "watches": 2, "content": {"raw": "Sometimes Atlas falls down on startup when the BDI stand behaviour kicks in too late. I was compiling gazebo while this happened so i had ~100% cpu usage, which might explain the lag, but also happens during normal operation sometimes I think (or maybe i'm always compiling something when this happens ...).", "markup": "markdown", "html": "<p>Sometimes Atlas falls down on startup when the BDI stand behaviour kicks in too late. I was compiling gazebo while this happened so i had ~100% cpu usage, which might explain the lag, but also happens during normal operation sometimes I think (or maybe i'm always compiling something when this happens ...).</p>", "type": "rendered"}, "assignee": null, "state": "resolved", "version": null, "edited_on": null, "created_on": "2013-04-27T22:23:50.789150+00:00", "milestone": null, "updated_on": "2013-05-02T19:34:10.723642+00:00", "type": "issue", "id": 225}