{"priority": "major", "kind": "bug", "repository": {"links": {"self": {"href": "data/repositories/osrf/drcsim.json"}, "html": {"href": "#!/osrf/drcsim"}, "avatar": {"href": "data/bytebucket.org/ravatar/{247b5408-ae91-4e3c-b2f9-a21994658d11}ts=c_plus_plus"}}, "type": "repository", "name": "drcsim", "full_name": "osrf/drcsim", "uuid": "{247b5408-ae91-4e3c-b2f9-a21994658d11}"}, "links": {"attachments": {"href": "data/repositories/osrf/drcsim/issues/486/attachments_page=1.json"}, "self": {"href": "data/repositories/osrf/drcsim/issues/486.json"}, "watch": {"href": "https://api.bitbucket.org/2.0/repositories/osrf/drcsim/issues/486/watch"}, "comments": {"href": "data/repositories/osrf/drcsim/issues/486/comments_page=1.json"}, "html": {"href": "#!/osrf/drcsim/issues/486/dart-not-working-on-drcsim"}, "vote": {"href": "https://api.bitbucket.org/2.0/repositories/osrf/drcsim/issues/486/vote"}}, "reporter": {"display_name": "Davide Faconti", "uuid": "{3bbc1820-fdbe-4162-b25e-fab777cc0f8d}", "links": {"self": {"href": "https://api.bitbucket.org/2.0/users/%7B3bbc1820-fdbe-4162-b25e-fab777cc0f8d%7D"}, "html": {"href": "https://bitbucket.org/%7B3bbc1820-fdbe-4162-b25e-fab777cc0f8d%7D/"}, "avatar": {"href": "https://avatar-management--avatars.us-west-2.prod.public.atl-paas.net/557058:1062128f-7772-4ea3-89d5-5ef7858df793/e350d3ea-077e-4a95-b81c-d41dc0012942/128"}}, "nickname": "facontidavide", "type": "user", "account_id": "557058:1062128f-7772-4ea3-89d5-5ef7858df793"}, "title": "DART not working on DRCSim", "component": null, "votes": 1, "watches": 4, "content": {"raw": "Hi,\r\n\r\nI have tried to use DART, but apparently it is not working on drcsim. On the other hand, it works fine on gazebo (same machine).\r\nThe GUI never show up and it is hard to know where the application is freezing; the only suspicious print is \r\n\r\n     [ INFO] [1423761842.792512293]: Finished loading Gazebo ROS API Plugin.\r\n     [ INFO] [1423761842.792891966]: waitForService: Service [/gazebo/set_physics_properties] has not been advertised, waiting...\r\n\r\n\r\nI am using ubuntu 14.04, and DART 4.3 (from debian package)\r\n\r\nAny suggestion?", "markup": "markdown", "html": "<p>Hi,</p>\n<p>I have tried to use DART, but apparently it is not working on drcsim. On the other hand, it works fine on gazebo (same machine).\nThe GUI never show up and it is hard to know where the application is freezing; the only suspicious print is </p>\n<div class=\"codehilite\"><pre><span></span> [ INFO] [1423761842.792512293]: Finished loading Gazebo ROS API Plugin.\n [ INFO] [1423761842.792891966]: waitForService: Service [/gazebo/set_physics_properties] has not been advertised, waiting...\n</pre></div>\n\n\n<p>I am using ubuntu 14.04, and DART 4.3 (from debian package)</p>\n<p>Any suggestion?</p>", "type": "rendered"}, "assignee": {"display_name": "Steve Peters", "uuid": "{2ccfed09-18b8-4921-8d58-15ef01092802}", "links": {"self": {"href": "https://api.bitbucket.org/2.0/users/%7B2ccfed09-18b8-4921-8d58-15ef01092802%7D"}, "html": {"href": "https://bitbucket.org/%7B2ccfed09-18b8-4921-8d58-15ef01092802%7D/"}, "avatar": {"href": "data/secure.gravatar.com/avatar/1fb4816dad9e68337d3096f750951f6cd=httpsavatar-management--avatars.us-west-2.prod.public.atl-paas.netinitialsSP-1.png"}}, "nickname": "Steven Peters", "type": "user", "account_id": "557058:5de38267-b118-494c-aa76-4fab35448816"}, "state": "new", "version": null, "edited_on": null, "created_on": "2015-02-12T17:26:25.159595+00:00", "milestone": null, "updated_on": "2015-03-06T18:52:21.760122+00:00", "type": "issue", "id": 486}